[
  {"content":"\r\nالتلخيص الحبير\r\nفي تخريج الرافعي الكبير\r\nللإمام أبي الفضل أحمد بن علي بن حجر العسقلاني المتوفى سنة 852 ه‍\r\nالجزء التاسع\r\nدار الفكر\r\n","description":"","footnote":"","page_name":" 1 ","page_number":1},
  {"content":"\r\n\r\nبسم الله الرحمن الرحيم\r\nباب الأصول والثمار\r\n","description":"","footnote":"","page_name":" 2 ","page_number":2},
  {"content":"\r\n\r\n","description":"","footnote":"","page_name":" 3 ","page_number":3},
  {"content":"\r\n\r\n","description":"","footnote":"","page_name":" 4 ","page_number":4},
  {"content":"\r\n\r\n","description":"","footnote":"","page_name":" 5 ","page_number":5},
  {"content":"\r\n\r\n","description":"","footnote":"","page_name":" 6 ","page_number":6},
  {"content":"\r\n\r\n","description":"","footnote":"","page_name":" 7 ","page_number":7},
  {"content":"\r\n\r\n","description":"","footnote":"","page_name":" 8 ","page_number":8},
  {"content":"\r\n\r\n","description":"","footnote":"","page_name":" 9 ","page_number":9},
  {"content":"\r\n\r\n","description":"","footnote":"","page_name":" 10 ","page_number":10},
  {"content":"\r\n\r\n","description":"","footnote":"","page_name":" 11 ","page_number":11},
  {"content":"\r\n\r\n","description":"","footnote":"","page_name":" 12 ","page_number":12},
  {"content":"\r\n\r\n","description":"","footnote":"","page_name":" 13 ","page_number":13},
  {"content":"\r\n\r\n","description":"","footnote":"","page_name":" 14 ","page_number":14},
  {"content":"\r\n\r\n","description":"","footnote":"","page_name":" 15 ","page_number":15},
  {"content":"\r\n\r\n","description":"","footnote":"","page_name":" 16 ","page_number":16},
  {"content":"\r\n\r\n","description":"","footnote":"","page_name":" 17 ","page_number":17},
  {"content":"\r\n\r\n","description":"","footnote":"","page_name":" 18 ","page_number":18},
  {"content":"\r\n\r\n","description":"","footnote":"","page_name":" 19 ","page_number":19},
  {"content":"\r\n\r\n","description":"","footnote":"","page_name":" 20 ","page_number":20},
  {"content":"\r\n\r\n","description":"","footnote":"","page_name":" 21 ","page_number":21},
  {"content":"\r\n\r\n","description":"","footnote":"","page_name":" 22 ","page_number":22},
  {"content":"\r\n\r\n","description":"","footnote":"","page_name":" 23 ","page_number":23},
  {"content":"\r\n\r\n","description":"","footnote":"","page_name":" 24 ","page_number":24},
  {"content":"\r\n\r\n","description":"","footnote":"","page_name":" 25 ","page_number":25},
  {"content":"\r\n\r\n","description":"","footnote":"","page_name":" 26 ","page_number":26},
  {"content":"\r\n\r\n","description":"","footnote":"","page_name":" 27 ","page_number":27},
  {"content":"\r\n\r\n","description":"","footnote":"","page_name":" 28 ","page_number":28},
  {"content":"\r\n\r\n","description":"","footnote":"","page_name":" 29 ","page_number":29},
  {"content":"\r\n\r\n","description":"","footnote":"","page_name":" 30 ","page_number":30},
  {"content":"\r\n\r\n","description":"","footnote":"","page_name":" 31 ","page_number":31},
  {"content":"\r\n\r\n","description":"","footnote":"","page_name":" 32 ","page_number":32},
  {"content":"\r\n\r\n","description":"","footnote":"","page_name":" 33 ","page_number":33},
  {"content":"\r\n\r\n","description":"","footnote":"","page_name":" 34 ","page_number":34},
  {"content":"\r\n\r\n","description":"","footnote":"","page_name":" 35 ","page_number":35},
  {"content":"\r\n\r\n","description":"","footnote":"","page_name":" 36 ","page_number":36},
  {"content":"\r\n\r\n","description":"","footnote":"","page_name":" 37 ","page_number":37},
  {"content":"\r\n\r\n","description":"","footnote":"","page_name":" 38 ","page_number":38},
  {"content":"\r\n\r\n","description":"","footnote":"","page_name":" 39 ","page_number":39},
  {"content":"\r\n( 1 ) * ( حديث ) * من باع نخلا بعد أن تؤبر فثمرتها للبائع إلا أن يشترط المبتاع . الشافعي عن\r\nابن عيينة عن الزهري عن سالم عن أبيه رواه مسلم واتفقا عليه من حديث مالك عن نافع عن ابن\r\nعمر بلفظ قد أبرت وأخرجه الشافعي أيضا عن مالك قال الشافعي هذا الحديث ثابت عندنا وبه نأخذ\r\n( تنبيه ) وقع في بعض نسخ الرافعي قبل ان تؤبر وهو غلط من الناسخ وكذا عزاه ابن الرفعة\r\nفي المطلب للمختصر فوهم وقد ذكره امام الحرمين في النهاية على المختصر على الصواب *\r\n( 2 ) ( حديث ) روى أن رجلا ابتاع نخلا من آخر واختلفا فقال المبتاع انا أبرته بعد\r\n","description":"","footnote":"","page_name":" 40 ","page_number":40},
  {"content":"\r\nما بتعت وقال البائع أنا أبرته قبل البيع فتحاكما إلى رسول الله صلى الله عليه وسلم فقضى بالثمرة لمن\r\nأبر منهما . البيهقي في المعرفة من طريق الشافعي من مرسل عطاء وعزاه ابن الطلاع في الأحكام إلى\r\nالدلائل للأصيلي مسندا عن ابن عمر *\r\n","description":"","footnote":"","page_name":" 41 ","page_number":41},
  {"content":"\r\n\r\n","description":"","footnote":"","page_name":" 42 ","page_number":42},
  {"content":"\r\n\r\n","description":"","footnote":"","page_name":" 43 ","page_number":43},
  {"content":"\r\n\r\n","description":"","footnote":"","page_name":" 44 ","page_number":44},
  {"content":"\r\n\r\n","description":"","footnote":"","page_name":" 45 ","page_number":45},
  {"content":"\r\n\r\n","description":"","footnote":"","page_name":" 46 ","page_number":46},
  {"content":"\r\n\r\n","description":"","footnote":"","page_name":" 47 ","page_number":47},
  {"content":"\r\n\r\n","description":"","footnote":"","page_name":" 48 ","page_number":48},
  {"content":"\r\n\r\n","description":"","footnote":"","page_name":" 49 ","page_number":49},
  {"content":"\r\n\r\n","description":"","footnote":"","page_name":" 50 ","page_number":50},
  {"content":"\r\n\r\n","description":"","footnote":"","page_name":" 51 ","page_number":51},
  {"content":"\r\n\r\n","description":"","footnote":"","page_name":" 52 ","page_number":52},
  {"content":"\r\n\r\n","description":"","footnote":"","page_name":" 53 ","page_number":53},
  {"content":"\r\n\r\n","description":"","footnote":"","page_name":" 54 ","page_number":54},
  {"content":"\r\n\r\n","description":"","footnote":"","page_name":" 55 ","page_number":55},
  {"content":"\r\n\r\n","description":"","footnote":"","page_name":" 56 ","page_number":56},
  {"content":"\r\n\r\n","description":"","footnote":"","page_name":" 57 ","page_number":57},
  {"content":"\r\n\r\n","description":"","footnote":"","page_name":" 58 ","page_number":58},
  {"content":"\r\n( 1 ) ( حديث ) أنه صلى الله عليه وسلم نهى عن بيع الثمار حتى تنجو من العاهة رواه الشافعي وغيره وقد تقدم *\r\n","description":"","footnote":"","page_name":" 59 ","page_number":59},
  {"content":"\r\n( 1 ) ( حديث ) أن النبي صلى الله عليه وسلم نهى عن بيع الثمار حتى يبدو صلاحها متفق عليه من\r\nحديث مالك عن نافع عن ابن عمر وأخرجه عن الشافعي في رواية لمسلم حتى يبدو صلاحه حمرته\r\nوصفرته وفى رواية له قال ما صلاحه قال تذهب عاهته وفى رواية لهما قيل لابن عمر وأخرجه مسلم عن\r\nجابر وأبي هريرة وفى البخاري عن سهل ابن أبي حثمة وغيره عن زيد ابن ثابت وفيه قصة *\r\n","description":"","footnote":"","page_name":" 60 ","page_number":60},
  {"content":"\r\n\r\n","description":"","footnote":"","page_name":" 61 ","page_number":61},
  {"content":"\r\n( 1 ) ( حديث ) انه صلى الله عليه وسلم قال أرأيت إذا منع الله الثمرة فبم يستحل أحدكم مال\r\nأخيه * متفق عليه من حديث أنس وقد بينت في المدلج أن هذه الجملة موقوفة من قول أنس وان دفعها وهم وبيانها عند مسلم *\r\n","description":"","footnote":"","page_name":" 62 ","page_number":62},
  {"content":"\r\n\r\n","description":"","footnote":"","page_name":" 63 ","page_number":63},
  {"content":"\r\n\r\n","description":"","footnote":"","page_name":" 64 ","page_number":64},
  {"content":"\r\n\r\n","description":"","footnote":"","page_name":" 65 ","page_number":65},
  {"content":"\r\n\r\n","description":"","footnote":"","page_name":" 66 ","page_number":66},
  {"content":"\r\n\r\n","description":"","footnote":"","page_name":" 67 ","page_number":67},
  {"content":"\r\n\r\n","description":"","footnote":"","page_name":" 68 ","page_number":68},
  {"content":"\r\n\r\n","description":"","footnote":"","page_name":" 69 ","page_number":69},
  {"content":"\r\n\r\n","description":"","footnote":"","page_name":" 70 ","page_number":70},
  {"content":"\r\n\r\n","description":"","footnote":"","page_name":" 71 ","page_number":71},
  {"content":"\r\n\r\n","description":"","footnote":"","page_name":" 72 ","page_number":72},
  {"content":"\r\n( 1 ) ( حديث ) نهى رسول الله صلى الله عليه وسلم عن بيع الثمار حتى تزهى فقيل يا رسول\r\nالله وما تزهى قال تحمر . أو تصفر : متفق عليه ولفظ مسلم حتى تحمار وتصفار وللبخاري عن جابر\r\nبلفظ حتى تشقح قيل وما تشقح قال تحمار وتصفار ويوكل منها وبين في مسلم ان السائل عن ذلك غير\r\nسعيد بن ميناء رواية عن جابر وللبزار باسناد صحيح عن طاووس عن ابن عباس بلفظ نهى عن بيع\r\nالثمار حتى تطعم ( تنبيه ) تزهى من ازهي وتزهو من زها وكلاهما مسموع حكاهما الجوهري\r\n","description":"","footnote":"","page_name":" 73 ","page_number":73},
  {"content":"\r\n\r\n","description":"","footnote":"","page_name":" 74 ","page_number":74},
  {"content":"\r\n\r\n","description":"","footnote":"","page_name":" 75 ","page_number":75},
  {"content":"\r\n\r\n","description":"","footnote":"","page_name":" 76 ","page_number":76},
  {"content":"\r\n\r\n","description":"","footnote":"","page_name":" 77 ","page_number":77},
  {"content":"\r\n\r\n","description":"","footnote":"","page_name":" 78 ","page_number":78},
  {"content":"\r\n\r\n","description":"","footnote":"","page_name":" 79 ","page_number":79},
  {"content":"\r\n\r\n","description":"","footnote":"","page_name":" 80 ","page_number":80},
  {"content":"\r\n\r\n","description":"","footnote":"","page_name":" 81 ","page_number":81},
  {"content":"\r\n\r\n","description":"","footnote":"","page_name":" 82 ","page_number":82},
  {"content":"\r\n( 1 ) ( حديث ) نهى عن بيع الحب حتى يشتد تقدم في أوائل البيوع عن انس *\r\n","description":"","footnote":"","page_name":" 83 ","page_number":83},
  {"content":"\r\n\r\n","description":"","footnote":"","page_name":" 84 ","page_number":84},
  {"content":"\r\n\r\n","description":"","footnote":"","page_name":" 85 ","page_number":85},
  {"content":"\r\n\r\n","description":"","footnote":"","page_name":" 86 ","page_number":86},
  {"content":"\r\n( 1 ) ( حديث ) نهى عن المحاقلة والمزابنة يأتي *\r\n( 2 ) ( حديث ) جابر أن النبي صلى الله عليه وسلم نهي عن المحاقلة والمزابنة والمحاقلة أن\r\nيبيع الرجل الزرع بمائة فرق من الحنطة والمزابنة أن يبيع التمر على رؤس النخل بمائة فرق من\r\nتمر : الشافعي في المختصر عن سفيان عن ابن جريج عن عطاء عنه قال ابن جريج قلت لعطاء أفسر لكم\r\n","description":"","footnote":"","page_name":" 87 ","page_number":87},
  {"content":"\r\nجابر المحاقلة كما أخبرتني قال نعم وهو متفق عليه من حديث سفيان نحوه واتفقا عن مالك عن نافع عن\r\nابن عمر بلفظ نهى عن المزابنة والمزابنة بيع التمر بالتمر كيلا وبيع الكرم بالزبيب كيلا وأخرجه عنه\r\nالشافعي في الام قال الشافعي وتفسير المحاقلة والمزابنة في الأحاديث يحتمل أن يكون النبي صلى الله عليه\r\nعليه وسلم منصوصا ويحتمل أن يكون من رواية من رواه انتهى * وفى الباب عن أبي سعيد وابن عمر\r\nوابن عباس وأنس وأبي هريرة وكلها في الصحيحين أو أحدهما وعن رافع بن خديج في النسائي وسهل\r\nابن سعد في الطبراني ( تنبيه ) المحاقلة مأخوذة من الحقل جمع حقلة قاله الجوهري وهي الساحات\r\nجمع ساحة *\r\n","description":"","footnote":"","page_name":" 88 ","page_number":88},
  {"content":"\r\n\r\n","description":"","footnote":"","page_name":" 89 ","page_number":89},
  {"content":"\r\n\r\n","description":"","footnote":"","page_name":" 90 ","page_number":90},
  {"content":"\r\n\r\n","description":"","footnote":"","page_name":" 91 ","page_number":91},
  {"content":"\r\n( 1 ) ( حديث ) جابر نهى عن المزابنة وهي بيع التمر بالتمر الا انه رخص في العرية . الشافعي عن\r\nسفيان عن ابن جريج عن عطاء عنه واتفق الشيخان عليه عن ابن عيينة *\r\n","description":"","footnote":"","page_name":" 92 ","page_number":92},
  {"content":"\r\n( 1 ) ( حديث ) سهل ابن أبي حثمة ان رسول الله صلى الله عليه وسلم نهى عن بيع التمر بالتمر\r\nالا انه رخص في العرية ان تباع بخرصها تمرا يأكلها أهلها رطبا . الشافعي واحمد والشيخان وغيرهما عنه *\r\n","description":"","footnote":"","page_name":" 93 ","page_number":93},
  {"content":"\r\n\r\n","description":"","footnote":"","page_name":" 94 ","page_number":94},
  {"content":"\r\n( 1 ) ( حديث ) روي الشافعي عن مالك عن داود وهو ابن الحصين عن أبي سفيان مولى ابن أبي\r\nاحمد عن أبي هريرة ان رسول الله صلى الله عليه وسلم ارخص في بيع العرايا بخرصها فيما دون\r\nخمسه أوسق أوفى خمسة أوسق شك داود . هو في الام والمختصر كذلك ورواه البخاري عن عبد الله بن\r\nعبد الوهاب الحجبي سمعت مالكا وسأله عبيد الله بن الربيع أحدثك داود عن أبي سفيان عن أبي هريرة\r\nفذكره دون ما في آخره وذكر في كتاب الشرب من صحيحه ذلك ورواه مسلم عن يحيى بن يحيى عن مالك *\r\n","description":"","footnote":"","page_name":" 95 ","page_number":95},
  {"content":"\r\n\r\n","description":"","footnote":"","page_name":" 96 ","page_number":96},
  {"content":"\r\n\r\n","description":"","footnote":"","page_name":" 97 ","page_number":97},
  {"content":"\r\n\r\n","description":"","footnote":"","page_name":" 98 ","page_number":98},
  {"content":"\r\n( 1 ) ( حديث ) زيد بن ثابت انه سمي رجالا محتاجين من الأنصار شكوا إلى رسول الله\r\nصلى الله عليه وسلم ان الرطب يأتي ولا نقد بأيديهم يبتاعون به رطبا يأكلونه مع الناس وعندهم\r\nفضول قوت من تمر فرخص لهم ان يبتاعوا العرايا بخرصها من التمر . هذا الحديث ذكره الشافعي في\r\nالام والمختصر بغير اسناد فقال قيل لمحمود بن لبيد أو قال محمود بن لبيد لرجل من أصحاب رسول الله\r\n","description":"","footnote":"","page_name":" 99 ","page_number":99},
  {"content":"\r\nصلى الله عليه وسلم اما زيد بن ثابت واما غيره ما عراياكم هذه . قال فلان وفلان وسمي رجالا محتاجين\r\nفذكره . وذكره في اختلاف الحديث فقال والعرايا التي ارخص فيها رسول الله صلى الله عليه وسلم فيما\r\nذكر محمود بن لبيد قال سألت زيد بن ثابت فقلت ما عراياكم هذه فذكر نحوه وذكره البيهقي في\r\nالمعرفة عن الشافعي معلقا أيضا وقد أنكره محمد بن داود على الشافعي ورد عليه ابن سريج انكاره\r\n","description":"","footnote":"","page_name":" 100 ","page_number":100},
  {"content":"\r\nولم يذكر له اسنادا وقال ابن جزم لم يذكر الشافعي له اسنادا فبطل أن يكون فيه حجة وقال\r\nالماوردي لم يسنده الشافعي لأنه نقله من السير ( تنبيه ) قال الشيخ الموفق في الكافي بعد أن ساق هذا\r\nالحديث متفق عليه وهو وهم منه\r\n","description":"","footnote":"","page_name":" 101 ","page_number":101},
  {"content":"\r\n( 1 ) ( حديث ) ان النبي صلى الله عليه وسلم امر بوضع الجوائح . مسلم عن جابر وفى لفظ\r\nللنسائي ان النبي صلى الله عليه وسلم وضع الجوائح *\r\n","description":"","footnote":"","page_name":" 102 ","page_number":102},
  {"content":"\r\n( 1 ) ( حديث ) ان رجلا ابتاع تمره فاذهبتها الجائحة فسأله ان يضع عنه فأبى ان لا يفعل\r\nفذكر ذلك للنبي صلى الله عليه وسلم فقال يأبى ان لا يفعل خيرا فأخبر البائع بما ذكر النبي صلى الله عليه وسلم فسمح به للمبتاع . الشافعي عن مالك عن أبي الرجال عن أمه عمرة به نحوه مرسل\r\n","description":"","footnote":"","page_name":" 103 ","page_number":103},
  {"content":"\r\nوالبيهقي من طريق حارثة بن أبي الرحال عن أبيه عن عمرة عن عائشة موصولا وقال حارثة ضعيف\r\nوهو في الصحيحين من طريق يحيى بن سعيد عن عمرة عن عائشة مختصرا *\r\n","description":"","footnote":"","page_name":" 104 ","page_number":104},
  {"content":"\r\n\r\n","description":"","footnote":"","page_name":" 105 ","page_number":105},
  {"content":"\r\n\r\n","description":"","footnote":"","page_name":" 106 ","page_number":106},
  {"content":"\r\n\r\n","description":"","footnote":"","page_name":" 107 ","page_number":107},
  {"content":"\r\n\r\n","description":"","footnote":"","page_name":" 108 ","page_number":108},
  {"content":"\r\n\r\n","description":"","footnote":"","page_name":" 109 ","page_number":109},
  {"content":"\r\n\r\n","description":"","footnote":"","page_name":" 110 ","page_number":110},
  {"content":"\r\n\r\n","description":"","footnote":"","page_name":" 111 ","page_number":111},
  {"content":"\r\n\r\n","description":"","footnote":"","page_name":" 112 ","page_number":112},
  {"content":"\r\n\r\n","description":"","footnote":"","page_name":" 113 ","page_number":113},
  {"content":"\r\n\r\n","description":"","footnote":"","page_name":" 114 ","page_number":114},
  {"content":"\r\n\r\n","description":"","footnote":"","page_name":" 115 ","page_number":115},
  {"content":"\r\n\r\n","description":"","footnote":"","page_name":" 116 ","page_number":116},
  {"content":"\r\n\r\n","description":"","footnote":"","page_name":" 117 ","page_number":117},
  {"content":"\r\n\r\n","description":"","footnote":"","page_name":" 118 ","page_number":118},
  {"content":"\r\n\r\n","description":"","footnote":"","page_name":" 119 ","page_number":119},
  {"content":"\r\n\r\n","description":"","footnote":"","page_name":" 120 ","page_number":120},
  {"content":"\r\n\r\n","description":"","footnote":"","page_name":" 121 ","page_number":121},
  {"content":"\r\n\r\n","description":"","footnote":"","page_name":" 122 ","page_number":122},
  {"content":"\r\n\r\n","description":"","footnote":"","page_name":" 123 ","page_number":123},
  {"content":"\r\n\r\n","description":"","footnote":"","page_name":" 124 ","page_number":124},
  {"content":"\r\n\r\n","description":"","footnote":"","page_name":" 125 ","page_number":125},
  {"content":"\r\n\r\n","description":"","footnote":"","page_name":" 126 ","page_number":126},
  {"content":"\r\n\r\n","description":"","footnote":"","page_name":" 127 ","page_number":127},
  {"content":"\r\n\r\n","description":"","footnote":"","page_name":" 128 ","page_number":128},
  {"content":"\r\n\r\n","description":"","footnote":"","page_name":" 129 ","page_number":129},
  {"content":"\r\n\r\n","description":"","footnote":"","page_name":" 130 ","page_number":130},
  {"content":"\r\n\r\n","description":"","footnote":"","page_name":" 131 ","page_number":131},
  {"content":"\r\n\r\n","description":"","footnote":"","page_name":" 132 ","page_number":132},
  {"content":"\r\n\r\n","description":"","footnote":"","page_name":" 133 ","page_number":133},
  {"content":"\r\n\r\n","description":"","footnote":"","page_name":" 134 ","page_number":134},
  {"content":"\r\n\r\n","description":"","footnote":"","page_name":" 135 ","page_number":135},
  {"content":"\r\n\r\n","description":"","footnote":"","page_name":" 136 ","page_number":136},
  {"content":"\r\n\r\n","description":"","footnote":"","page_name":" 137 ","page_number":137},
  {"content":"\r\n\r\n","description":"","footnote":"","page_name":" 138 ","page_number":138},
  {"content":"\r\n\r\n","description":"","footnote":"","page_name":" 139 ","page_number":139},
  {"content":"\r\n\r\n","description":"","footnote":"","page_name":" 140 ","page_number":140},
  {"content":"\r\n\r\n","description":"","footnote":"","page_name":" 141 ","page_number":141},
  {"content":"\r\n\r\n","description":"","footnote":"","page_name":" 142 ","page_number":142},
  {"content":"\r\n\r\n","description":"","footnote":"","page_name":" 143 ","page_number":143},
  {"content":"\r\n\r\n","description":"","footnote":"","page_name":" 144 ","page_number":144},
  {"content":"\r\n\r\n","description":"","footnote":"","page_name":" 145 ","page_number":145},
  {"content":"\r\n\r\n","description":"","footnote":"","page_name":" 146 ","page_number":146},
  {"content":"\r\n\r\n( باب معاملات العبيد )\r\n( 1 ) ( حديث ) من باع عبدا وله مال الحديث : متفق عليه من حديث ابن عمر ولأبي داود\r\nوابن حبان عن جابر نحوه وللبيهقي من حديث عبادة بن الصامت نحوه *\r\n","description":"","footnote":"","page_name":" 147 ","page_number":147},
  {"content":"\r\n\r\n","description":"","footnote":"","page_name":" 148 ","page_number":148},
  {"content":"\r\n\r\n( باب اختلاف المتبايعين )\r\n","description":"","footnote":"","page_name":" 149 ","page_number":149},
  {"content":"\r\n( 1 ) ( قوله ) وفى رواية إذا اختلف المتبايعان تحالفا وفى رواية أخري تحالفا أو ترادا أما\r\nرواية التحالف فاعترف الرافعي في التذنيب أنه لا ذكر لها في شئ من كتب الحديث وإنما توجد في\r\nكتب الفقه وكأنه عني الغزالي فإنه ذكرها في الوسيط وهو تبع امامه في الأساليب وأما رواية التراد\r\nفرواها مالك بلاغا عن ابن مسعود ورواها أحمد والترمذي وابن ماجة باسناد منقطع وقال الطبراني\r\nفي الكبير . نا محمد بن هشام المستملي نا عبد الرحمن بن صالح نا فضيل بن عياض نا منصور عن إبراهيم\r\n","description":"","footnote":"","page_name":" 150 ","page_number":150},
  {"content":"\r\nعن علقمة عن عبد الله مرفوعا البيعان إذا اختلفا في البيع ترادا رواته ثقات لكن اختلف في\r\nعبد الرحمن بن صالح وما أظنه حفظه فقد جزم الشافعي أن طرق هذا الحديث عن ابن مسعود\r\nليس فيها شئ موصول وذكر الدارقطني علله فلم يعرج على هذه الطريق وله طريق أخري عند أبي\r\nداود والنسائي والحاكم والبيهقي من طريق عبد الرحمن بن قيس بن محمد بن الأشعث عن أبيه\r\nعن جده قال قال عبد الله بن مسعود فذكر الحديث وصححه من هذا الوجه الحاكم وحسنه البيهقي\r\nوقال ابن عبد البر هو منقطع إلا أنه مشهور الأصل عند جماعه العلماء تلقوه بالقبول وبنوا عليه كثيرا\r\nمن فروعه وأعله ابن حزم بالانقطاع وتابعه عبد الحق وأعله بن القطان بالجهالة في عبد الرحمن وأبيه\r\nوجده وله طريق اخري رواها الدارقطني من طريق القاسم بن عبد الرحمن بن عبد الله بن مسعود\r\nعن أبيه قال باع عبد الله بن مسعود سبيا من سبى الامارة بعشرين ألفا يعنى من الأشعث بن قيس\r\nفذكر القصة والحديث ورجاله ثقات إلا أن عبد الرحمن اختلف في سماعه من أبيه *\r\n","description":"","footnote":"","page_name":" 151 ","page_number":151},
  {"content":"\r\n( 1 ) ( حديث ) ابن مسعود أن النبي صلى الله عليه وسلم قال إذا اختلف المتبايعان فالقول قول البائع\r\nوالمبتاع بالخيار . الشافعي عن سعيد بن سالم عن ابن جريج عن إسماعيل بن أمية عن عبد الملك بن عمير\r\nعن أبي عبيدة بن عبد الله بن مسعود قال أتى عبد الله بن مسعود فقال حضرت النبي صلى الله عليه وسلم فامر\r\nبالبائع أن يستحلف ثم يخير المبتاع إن شاء أخذ وإن شاء ترك رواه أحمد عن الشافعي والنسائي\r\nوالدارقطني من طريق أبى عبيده أيضا وفيه انقطاع على ما عرف من اختلافهم في صحة سماع أبى عبيدة\r\nمن أبيه واختلف فيه على إسماعيل بن أمية ثم عن ابن جريج في تسمية والد عبد الملك هذا الراوي\r\nعن أبي عبيده فقال يحيى بن سليم عن إسماعيل بن أمية عبد الملك بن عمير كما قال سعيد بن سالم ووقع\r\nفي النسائي عبد الملك بن عبيد ورجح هذا أحمد والبيهقي وهو ظاهر كلام البخاري وقد صححه\r\nابن السكن والحاكم وروى الشافعي في المختصر عن سفيان عن ابن عجلان عن عون بن عبد الله\r\nابن عتبة بن مسعود عن ابن مسعود نحوه بلفظ الباب وفيه انقطاع ورواه الدارقطني من طريق\r\nالقاسم بن عبد الرحمن بن عبد الله بن مسعود عن أبيه عن جده وفيه إسماعيل بن عياش عن موسى\r\nابن عقبة *\r\n( قوله ) وفى رواية إذا اختلفا المتبايعان والسلعة قائمة ولا بينة لأحدهما تحالفا رواها\r\nعبد الله بن أحمد في زيادات المسند من طريق القاسم بن عبد الرحمن عن جده ورواها الطبراني\r\nوالدارمي من هذا الوجه فقال عن القاسم عن أبيه عن ابن مسعود وانفرد بهذه الزيادة وهي قوله\r\n","description":"","footnote":"","page_name":" 152 ","page_number":152},
  {"content":"\r\nوالسلعة قائمة عن أبي ليلى وهو محمد بن عبد الرحمن الفقيه وهو ضعيف سئ الحفظ وأما قوله فيه\r\nتحالفا فلم يقع عند أحد منهم وإنما عندهم والقول قول البائع أو يرادان *\r\n","description":"","footnote":"","page_name":" 153 ","page_number":153},
  {"content":"\r\n\r\n","description":"","footnote":"","page_name":" 154 ","page_number":154},
  {"content":"\r\n\r\n","description":"","footnote":"","page_name":" 155 ","page_number":155},
  {"content":"\r\n\r\n","description":"","footnote":"","page_name":" 156 ","page_number":156},
  {"content":"\r\n\r\n","description":"","footnote":"","page_name":" 157 ","page_number":157},
  {"content":"\r\n\r\n","description":"","footnote":"","page_name":" 158 ","page_number":158},
  {"content":"\r\n\r\n","description":"","footnote":"","page_name":" 159 ","page_number":159},
  {"content":"\r\n\r\n","description":"","footnote":"","page_name":" 160 ","page_number":160},
  {"content":"\r\n\r\n","description":"","footnote":"","page_name":" 161 ","page_number":161},
  {"content":"\r\n\r\n","description":"","footnote":"","page_name":" 162 ","page_number":162},
  {"content":"\r\n\r\n","description":"","footnote":"","page_name":" 163 ","page_number":163},
  {"content":"\r\n\r\n","description":"","footnote":"","page_name":" 164 ","page_number":164},
  {"content":"\r\n\r\n","description":"","footnote":"","page_name":" 165 ","page_number":165},
  {"content":"\r\n\r\n","description":"","footnote":"","page_name":" 166 ","page_number":166},
  {"content":"\r\n\r\n","description":"","footnote":"","page_name":" 167 ","page_number":167},
  {"content":"\r\n\r\n","description":"","footnote":"","page_name":" 168 ","page_number":168},
  {"content":"\r\n\r\n","description":"","footnote":"","page_name":" 169 ","page_number":169},
  {"content":"\r\n\r\n","description":"","footnote":"","page_name":" 170 ","page_number":170},
  {"content":"\r\n\r\n","description":"","footnote":"","page_name":" 171 ","page_number":171},
  {"content":"\r\n\r\n","description":"","footnote":"","page_name":" 172 ","page_number":172},
  {"content":"\r\n\r\n","description":"","footnote":"","page_name":" 173 ","page_number":173},
  {"content":"\r\n\r\n","description":"","footnote":"","page_name":" 174 ","page_number":174},
  {"content":"\r\n\r\n","description":"","footnote":"","page_name":" 175 ","page_number":175},
  {"content":"\r\n\r\n","description":"","footnote":"","page_name":" 176 ","page_number":176},
  {"content":"\r\n\r\n","description":"","footnote":"","page_name":" 177 ","page_number":177},
  {"content":"\r\n\r\n","description":"","footnote":"","page_name":" 178 ","page_number":178},
  {"content":"\r\n\r\n","description":"","footnote":"","page_name":" 179 ","page_number":179},
  {"content":"\r\n\r\n","description":"","footnote":"","page_name":" 180 ","page_number":180},
  {"content":"\r\n\r\n","description":"","footnote":"","page_name":" 181 ","page_number":181},
  {"content":"\r\n\r\n","description":"","footnote":"","page_name":" 182 ","page_number":182},
  {"content":"\r\n\r\n","description":"","footnote":"","page_name":" 183 ","page_number":183},
  {"content":"\r\n\r\n","description":"","footnote":"","page_name":" 184 ","page_number":184},
  {"content":"\r\n\r\n","description":"","footnote":"","page_name":" 185 ","page_number":185},
  {"content":"\r\n\r\n","description":"","footnote":"","page_name":" 186 ","page_number":186},
  {"content":"\r\n\r\n","description":"","footnote":"","page_name":" 187 ","page_number":187},
  {"content":"\r\n\r\n","description":"","footnote":"","page_name":" 188 ","page_number":188},
  {"content":"\r\n\r\n","description":"","footnote":"","page_name":" 189 ","page_number":189},
  {"content":"\r\n\r\n","description":"","footnote":"","page_name":" 190 ","page_number":190},
  {"content":"\r\n\r\n","description":"","footnote":"","page_name":" 191 ","page_number":191},
  {"content":"\r\n\r\n","description":"","footnote":"","page_name":" 192 ","page_number":192},
  {"content":"\r\n\r\n","description":"","footnote":"","page_name":" 193 ","page_number":193},
  {"content":"\r\n\r\n","description":"","footnote":"","page_name":" 194 ","page_number":194},
  {"content":"\r\n\r\n","description":"","footnote":"","page_name":" 195 ","page_number":195},
  {"content":"\r\n\r\n","description":"","footnote":"","page_name":" 196 ","page_number":196},
  {"content":"\r\n\r\n","description":"","footnote":"","page_name":" 197 ","page_number":197},
  {"content":"\r\n\r\n","description":"","footnote":"","page_name":" 198 ","page_number":198},
  {"content":"\r\n\r\n","description":"","footnote":"","page_name":" 199 ","page_number":199},
  {"content":"\r\n\r\n","description":"","footnote":"","page_name":" 200 ","page_number":200},
  {"content":"\r\n\r\n","description":"","footnote":"","page_name":" 201 ","page_number":201},
  {"content":"\r\n\r\n","description":"","footnote":"","page_name":" 202 ","page_number":202},
  {"content":"\r\n\r\n","description":"","footnote":"","page_name":" 203 ","page_number":203},
  {"content":"\r\n\r\n","description":"","footnote":"","page_name":" 204 ","page_number":204},
  {"content":"\r\n\r\nكتاب السلم\r\n","description":"","footnote":"","page_name":" 205 ","page_number":205},
  {"content":"\r\n( 1 ) قوله عن ابن عباس أن المراد بقوله تعالى إذا تداينتم بدين إلى اجل مسمى السلم\r\nالشافعي والطبراني والحاكم والبيهقي من طريق قتادة عن أبي حسان الأعرج عن ابن عباس قال\r\nأشهد أن السلف المضمون إلى أجل مسمى مما أحل الله في الكتاب واذن فيه قال الله تعالى\r\nيا أيها الذين آمنوا إذا تداينتم الآية وقد علقه البخاري وأوضحته في تعليق التعليق\r\n( 2 ) حديث أنه صلى الله عليه وسلم قدم المدينة وهم يسلفون في التمر السنة والسنتين وربما قال والثلاث\r\n","description":"","footnote":"","page_name":" 206 ","page_number":206},
  {"content":"\r\nفقال من أسلف فليسلف في كيل معلوم ووزن معلوم إلى أجل معلوم . الشافعي عن ابن عيينة\r\nعن ابن عبد الله بن كثير عن أبي المنهال عن ابن عباس ولفظه في التمر السنة والسنتين وربما\r\nقال السنتين والثلاث واتفقا عليه من حديث سفيان *\r\n","description":"","footnote":"","page_name":" 207 ","page_number":207},
  {"content":"\r\n\r\n","description":"","footnote":"","page_name":" 208 ","page_number":208},
  {"content":"\r\n\r\n","description":"","footnote":"","page_name":" 209 ","page_number":209},
  {"content":"\r\n\r\n","description":"","footnote":"","page_name":" 210 ","page_number":210},
  {"content":"\r\n\r\n","description":"","footnote":"","page_name":" 211 ","page_number":211},
  {"content":"\r\n\r\n","description":"","footnote":"","page_name":" 212 ","page_number":212},
  {"content":"\r\n\r\n","description":"","footnote":"","page_name":" 213 ","page_number":213},
  {"content":"\r\n\r\n","description":"","footnote":"","page_name":" 214 ","page_number":214},
  {"content":"\r\n\r\n","description":"","footnote":"","page_name":" 215 ","page_number":215},
  {"content":"\r\n\r\n","description":"","footnote":"","page_name":" 216 ","page_number":216},
  {"content":"\r\n\r\n","description":"","footnote":"","page_name":" 217 ","page_number":217},
  {"content":"\r\n\r\n","description":"","footnote":"","page_name":" 218 ","page_number":218},
  {"content":"\r\n\r\n","description":"","footnote":"","page_name":" 219 ","page_number":219},
  {"content":"\r\n\r\n","description":"","footnote":"","page_name":" 220 ","page_number":220},
  {"content":"\r\n\r\n","description":"","footnote":"","page_name":" 221 ","page_number":221},
  {"content":"\r\n\r\n","description":"","footnote":"","page_name":" 222 ","page_number":222},
  {"content":"\r\n\r\n","description":"","footnote":"","page_name":" 223 ","page_number":223},
  {"content":"\r\n\r\n","description":"","footnote":"","page_name":" 224 ","page_number":224},
  {"content":"\r\n\r\n","description":"","footnote":"","page_name":" 225 ","page_number":225},
  {"content":"\r\n\r\n","description":"","footnote":"","page_name":" 226 ","page_number":226},
  {"content":"\r\n\r\n","description":"","footnote":"","page_name":" 227 ","page_number":227},
  {"content":"\r\n\r\n","description":"","footnote":"","page_name":" 228 ","page_number":228},
  {"content":"\r\n\r\n","description":"","footnote":"","page_name":" 229 ","page_number":229},
  {"content":"\r\n\r\n","description":"","footnote":"","page_name":" 230 ","page_number":230},
  {"content":"\r\n\r\n","description":"","footnote":"","page_name":" 231 ","page_number":231},
  {"content":"\r\n( 1 ) حديث انه اشترى من يهودي إلى ميسرة . الترمذي والنسائي والحاكم من حديث عكرمة عن عائشة وفيه\r\nقصه قال الحاكم صحيح على شرط البخاري ورواه أحمد من طريق الربيع بن أنس عن أنس بن\r\nملك باسناد ضعيف قال أبو حاتم هو منكر وهو عند الطبراني في الأوسط من طريق عاصم الأحول\r\nعن انس ( تنبيه ) أعل ابن المنذر فيما نقله ابن الصباغ في الشامل حديث عائشة بحري بن عمارة وقال\r\nإنه رواه عن شعبة وقد قال فيه أحمد بن حنبل انه صدوق الا ان فيه غفلة قال ابن المنذر وهذا\r\nلم يتابع عليه فأخاف أن يكون من غفلاته اه‍ وهذا في الحقيقة من غفلات المعلل ولم ينفرد به\r\n","description":"","footnote":"","page_name":" 232 ","page_number":232},
  {"content":"\r\nحري بل لم نره من روايته إنما رواه شعبة عن والده عمارة عن عكرمة وكان حري حاضرا في المجلس\r\nبينه الترمذي والبيهقي *\r\n","description":"","footnote":"","page_name":" 233 ","page_number":233},
  {"content":"\r\n\r\n","description":"","footnote":"","page_name":" 234 ","page_number":234},
  {"content":"\r\n\r\n","description":"","footnote":"","page_name":" 235 ","page_number":235},
  {"content":"\r\n\r\n","description":"","footnote":"","page_name":" 236 ","page_number":236},
  {"content":"\r\n\r\n","description":"","footnote":"","page_name":" 237 ","page_number":237},
  {"content":"\r\n\r\n","description":"","footnote":"","page_name":" 238 ","page_number":238},
  {"content":"\r\n\r\n","description":"","footnote":"","page_name":" 239 ","page_number":239},
  {"content":"\r\n\r\n","description":"","footnote":"","page_name":" 240 ","page_number":240},
  {"content":"\r\n\r\n","description":"","footnote":"","page_name":" 241 ","page_number":241},
  {"content":"\r\n\r\n","description":"","footnote":"","page_name":" 242 ","page_number":242},
  {"content":"\r\n\r\n","description":"","footnote":"","page_name":" 243 ","page_number":243},
  {"content":"\r\n\r\n","description":"","footnote":"","page_name":" 244 ","page_number":244},
  {"content":"\r\n\r\n","description":"","footnote":"","page_name":" 245 ","page_number":245},
  {"content":"\r\n\r\n","description":"","footnote":"","page_name":" 246 ","page_number":246},
  {"content":"\r\n\r\n","description":"","footnote":"","page_name":" 247 ","page_number":247},
  {"content":"\r\n\r\n","description":"","footnote":"","page_name":" 248 ","page_number":248},
  {"content":"\r\n\r\n","description":"","footnote":"","page_name":" 249 ","page_number":249},
  {"content":"\r\n\r\n","description":"","footnote":"","page_name":" 250 ","page_number":250},
  {"content":"\r\n\r\n","description":"","footnote":"","page_name":" 251 ","page_number":251},
  {"content":"\r\n\r\n","description":"","footnote":"","page_name":" 252 ","page_number":252},
  {"content":"\r\n\r\n","description":"","footnote":"","page_name":" 253 ","page_number":253},
  {"content":"\r\n\r\n","description":"","footnote":"","page_name":" 254 ","page_number":254},
  {"content":"\r\n\r\n","description":"","footnote":"","page_name":" 255 ","page_number":255},
  {"content":"\r\n\r\n","description":"","footnote":"","page_name":" 256 ","page_number":256},
  {"content":"\r\n\r\n","description":"","footnote":"","page_name":" 257 ","page_number":257},
  {"content":"\r\n\r\n","description":"","footnote":"","page_name":" 258 ","page_number":258},
  {"content":"\r\n\r\n","description":"","footnote":"","page_name":" 259 ","page_number":259},
  {"content":"\r\n\r\n","description":"","footnote":"","page_name":" 260 ","page_number":260},
  {"content":"\r\n\r\n","description":"","footnote":"","page_name":" 261 ","page_number":261},
  {"content":"\r\n\r\n","description":"","footnote":"","page_name":" 262 ","page_number":262},
  {"content":"\r\n\r\n","description":"","footnote":"","page_name":" 263 ","page_number":263},
  {"content":"\r\n\r\n","description":"","footnote":"","page_name":" 264 ","page_number":264},
  {"content":"\r\n\r\n","description":"","footnote":"","page_name":" 265 ","page_number":265},
  {"content":"\r\n\r\n","description":"","footnote":"","page_name":" 266 ","page_number":266},
  {"content":"\r\n\r\n","description":"","footnote":"","page_name":" 267 ","page_number":267},
  {"content":"\r\n\r\n","description":"","footnote":"","page_name":" 268 ","page_number":268},
  {"content":"\r\n\r\n","description":"","footnote":"","page_name":" 269 ","page_number":269},
  {"content":"\r\n\r\n","description":"","footnote":"","page_name":" 270 ","page_number":270},
  {"content":"\r\n\r\n","description":"","footnote":"","page_name":" 271 ","page_number":271},
  {"content":"\r\n\r\n","description":"","footnote":"","page_name":" 272 ","page_number":272},
  {"content":"\r\n\r\n","description":"","footnote":"","page_name":" 273 ","page_number":273},
  {"content":"\r\n\r\n","description":"","footnote":"","page_name":" 274 ","page_number":274},
  {"content":"\r\n\r\n","description":"","footnote":"","page_name":" 275 ","page_number":275},
  {"content":"\r\n\r\n","description":"","footnote":"","page_name":" 276 ","page_number":276},
  {"content":"\r\n\r\n","description":"","footnote":"","page_name":" 277 ","page_number":277},
  {"content":"\r\n\r\n","description":"","footnote":"","page_name":" 278 ","page_number":278},
  {"content":"\r\n\r\n","description":"","footnote":"","page_name":" 279 ","page_number":279},
  {"content":"\r\n\r\n","description":"","footnote":"","page_name":" 280 ","page_number":280},
  {"content":"\r\n\r\n","description":"","footnote":"","page_name":" 281 ","page_number":281},
  {"content":"\r\n\r\n","description":"","footnote":"","page_name":" 282 ","page_number":282},
  {"content":"\r\n\r\n","description":"","footnote":"","page_name":" 283 ","page_number":283},
  {"content":"\r\n\r\n","description":"","footnote":"","page_name":" 284 ","page_number":284},
  {"content":"\r\n( 1 ) حديث عبد الله بن عمرو أمرني رسول الله صلى الله عليه وسلم أن اشترى له بعيرا ببعيرين\r\nإلى أجل أخرجه أبو داود وقد تقدم في الربا\r\n","description":"","footnote":"","page_name":" 285 ","page_number":285},
  {"content":"\r\n( 1 ) حديث ابن عمر أنه اشترى راحلة بأربعة أبعرة يوفيها صاحبها بالربذة : علقه البخاري\r\nورواه مالك في الموطأ عن نافع عن بن عمر والشافعي عن مالك كذلك ( تنبيه ) روى عن ابن عمر\r\nما يعارض هذا رواه عبد الرزاق عن معمر عن ابن طاووس عن أبيه أنه سأل ابن عمر عن\r\nبعير ببعيرين فكرهه ورواه ابن أبي شيبة عن ابن أبي زائدة عن ابن عون عن ابن سيرين\r\nقلت لابن عمر البعير بالبعيرين إلى أجل فكرهه ويمكن الجمع بأنه كان يرى فيه الجواز وإن كان\r\nمكروها على التنزيه لا على التحريم وروى الحاكم والدارقطني من حديث ابن عباس أن\r\nالنبي صلى الله عليه وسلم نهى عن السلف في الحيوان وفى اسناده إسحاق بن إبراهيم بن جوئي\r\nواه ابن حيان *\r\n( 2 ) حديث على أنه باع بعيرا بعشرين بعيرا إلى أجل مالك في الموطأ عن صالح عن\r\n","description":"","footnote":"","page_name":" 286 ","page_number":286},
  {"content":"\r\nالحسن بن محمد بن علي عن علي وفيه انقطاع بين الحسن وعلى وقد روى عنه ما يعارض هذا\r\nروى عبد الرزاق من طريق ابن المسيب عن علي أنه كره بعيرا ببعيرين نسيئة وروى ابن أبي\r\nشيبة نحوه عنه *\r\n","description":"","footnote":"","page_name":" 287 ","page_number":287},
  {"content":"\r\n\r\n","description":"","footnote":"","page_name":" 288 ","page_number":288},
  {"content":"\r\n\r\n","description":"","footnote":"","page_name":" 289 ","page_number":289},
  {"content":"\r\n\r\n","description":"","footnote":"","page_name":" 290 ","page_number":290},
  {"content":"\r\n\r\n","description":"","footnote":"","page_name":" 291 ","page_number":291},
  {"content":"\r\n\r\n","description":"","footnote":"","page_name":" 292 ","page_number":292},
  {"content":"\r\n\r\n","description":"","footnote":"","page_name":" 293 ","page_number":293},
  {"content":"\r\n\r\n","description":"","footnote":"","page_name":" 294 ","page_number":294},
  {"content":"\r\n\r\n","description":"","footnote":"","page_name":" 295 ","page_number":295},
  {"content":"\r\n\r\n","description":"","footnote":"","page_name":" 296 ","page_number":296},
  {"content":"\r\n\r\n","description":"","footnote":"","page_name":" 297 ","page_number":297},
  {"content":"\r\n\r\n","description":"","footnote":"","page_name":" 298 ","page_number":298},
  {"content":"\r\n\r\n","description":"","footnote":"","page_name":" 299 ","page_number":299},
  {"content":"\r\n\r\n","description":"","footnote":"","page_name":" 300 ","page_number":300},
  {"content":"\r\n\r\n","description":"","footnote":"","page_name":" 301 ","page_number":301},
  {"content":"\r\n\r\n","description":"","footnote":"","page_name":" 302 ","page_number":302},
  {"content":"\r\n\r\n","description":"","footnote":"","page_name":" 303 ","page_number":303},
  {"content":"\r\n\r\n","description":"","footnote":"","page_name":" 304 ","page_number":304},
  {"content":"\r\n\r\n","description":"","footnote":"","page_name":" 305 ","page_number":305},
  {"content":"\r\n\r\n","description":"","footnote":"","page_name":" 306 ","page_number":306},
  {"content":"\r\n\r\n","description":"","footnote":"","page_name":" 307 ","page_number":307},
  {"content":"\r\n\r\n","description":"","footnote":"","page_name":" 308 ","page_number":308},
  {"content":"\r\n\r\n","description":"","footnote":"","page_name":" 309 ","page_number":309},
  {"content":"\r\n\r\n","description":"","footnote":"","page_name":" 310 ","page_number":310},
  {"content":"\r\n\r\n","description":"","footnote":"","page_name":" 311 ","page_number":311},
  {"content":"\r\n\r\n","description":"","footnote":"","page_name":" 312 ","page_number":312},
  {"content":"\r\n\r\n","description":"","footnote":"","page_name":" 313 ","page_number":313},
  {"content":"\r\n\r\n","description":"","footnote":"","page_name":" 314 ","page_number":314},
  {"content":"\r\n\r\n","description":"","footnote":"","page_name":" 315 ","page_number":315},
  {"content":"\r\n\r\n","description":"","footnote":"","page_name":" 316 ","page_number":316},
  {"content":"\r\n\r\n","description":"","footnote":"","page_name":" 317 ","page_number":317},
  {"content":"\r\n\r\n","description":"","footnote":"","page_name":" 318 ","page_number":318},
  {"content":"\r\n\r\n","description":"","footnote":"","page_name":" 319 ","page_number":319},
  {"content":"\r\n\r\n","description":"","footnote":"","page_name":" 320 ","page_number":320},
  {"content":"\r\n\r\n","description":"","footnote":"","page_name":" 321 ","page_number":321},
  {"content":"\r\n\r\n","description":"","footnote":"","page_name":" 322 ","page_number":322},
  {"content":"\r\n\r\n","description":"","footnote":"","page_name":" 323 ","page_number":323},
  {"content":"\r\n\r\n","description":"","footnote":"","page_name":" 324 ","page_number":324},
  {"content":"\r\n\r\n","description":"","footnote":"","page_name":" 325 ","page_number":325},
  {"content":"\r\n\r\n","description":"","footnote":"","page_name":" 326 ","page_number":326},
  {"content":"\r\n\r\n","description":"","footnote":"","page_name":" 327 ","page_number":327},
  {"content":"\r\n\r\n","description":"","footnote":"","page_name":" 328 ","page_number":328},
  {"content":"\r\n\r\n","description":"","footnote":"","page_name":" 329 ","page_number":329},
  {"content":"\r\n\r\n","description":"","footnote":"","page_name":" 330 ","page_number":330},
  {"content":"\r\n\r\n","description":"","footnote":"","page_name":" 331 ","page_number":331},
  {"content":"\r\n\r\n","description":"","footnote":"","page_name":" 332 ","page_number":332},
  {"content":"\r\n\r\n","description":"","footnote":"","page_name":" 333 ","page_number":333},
  {"content":"\r\n\r\n","description":"","footnote":"","page_name":" 334 ","page_number":334},
  {"content":"\r\n\r\n","description":"","footnote":"","page_name":" 335 ","page_number":335},
  {"content":"\r\n\r\n","description":"","footnote":"","page_name":" 336 ","page_number":336},
  {"content":"\r\n( 1 ) حديث أن أنسا كاتب عبدا له على مال فجاء العبد بالمال فلم يقبله أنس فأتي العبد\r\nعمر فأخذه منه ووضعه في بيت المال . هذا الأثر الذي ذكره الشافعي في الام بلا اسناد وقد\r\nرواه البيهقي من طريق أنس بن سيرين عن أبيه قال كاتبني أنس على عشرين ألف درهم فكنت\r\nفيمن فتح تستر فاشتريت رقة فربحت فيها فأتيت أنسا بكتابتي فذكره ) *\r\n","description":"","footnote":"","page_name":" 337 ","page_number":337},
  {"content":"\r\n\r\n","description":"","footnote":"","page_name":" 338 ","page_number":338},
  {"content":"\r\n\r\n","description":"","footnote":"","page_name":" 339 ","page_number":339},
  {"content":"\r\n\r\n","description":"","footnote":"","page_name":" 340 ","page_number":340},
  {"content":"\r\n\r\n","description":"","footnote":"","page_name":" 341 ","page_number":341},
  {"content":"\r\n( 1 ) ( تنبيه ) وجد في النسخة التي بأيدينا بعد هذا قوله الخلط في البلد حرام لا ينحصر الخ\r\nولما كان الكلام غير مرتبط بما قبله رجعنا إلى المتن فوجد أنه قد سقط منه جملة لم تذكر\r\nفي الأصل الذي بأيدينا وهي من أول قوله ولا يجوز مبايعته قد يعلم الخ وتبين أن قوله الخلط\r\nفي البلد حرام يرتبط بها وقد سقط من أول شرحها إلى هنا جملة لم نهتد لها كما أنه لا يعلم أن كان\r\nقد سقط من شرح الأول بعد قوله نهى عن بيع الغرر سئ أم لا فليحرر *\r\n","description":"","footnote":"","page_name":" 342 ","page_number":342},
  {"content":"\r\n\r\n","description":"","footnote":"","page_name":" 343 ","page_number":343},
  {"content":"\r\n\r\n","description":"","footnote":"","page_name":" 344 ","page_number":344},
  {"content":"\r\n\r\n","description":"","footnote":"","page_name":" 345 ","page_number":345},
  {"content":"\r\n( باب القرض ) ( 1 ) حديث أنه صلى الله عليه وسلم استقرض بكرا ورد بازلا : هذا اللفظ تبع فيه الغزالي في الوسيط وهو\r\nتبع الامام في النهاية وزاد أنه صح والذي في الصحيحين عن أبي هريرة كان لرجل على رسول\r\nالله صلى الله عليه وسلم حق فأغلظ له فهم به أصحابه فقال دعوه فان لصاحب الحق مقالا فقال لهم اشتروا\r\nله سنا فاعطوه إياه فقالوا انا لا نجد الا سنا هو خير من سنه قال فاشتروه فاعطوه إياه فان من\r\nخيركم أو خيركم أحسنكم قضاء وأخرج مسلم عن أبي رافع أنه صلى الله عليه وسلم استسلف من رجل بكرا\r\nفقدمت عليه إبل من الصدقة فامر أبا رافع أن يعطي الرجل بكره فرجع إليه أبو رافع فقال لم\r\nأجد فيها الا خيارا رباعيا فأمره أن يعطيه الحديث وقد ذكره الرافقي بعد ( تنبيه ) البكر\r\n","description":"","footnote":"","page_name":" 346 ","page_number":346},
  {"content":"\r\nالصغير من الإبل والرباعي بفتح الراء ماله ست سنين وأما البازل فهو ماله ثمان سنين ودخل في\r\nالتاسعة فتبين أنهم لم يوردوا الحديث بلفظه ولا بمعناه وقد أخرج النسائي والبزار من حديث\r\nالعرباض بن سارية قال بعت من النبي صلى الله عليه وسلم بكرا فاتيته أتقاضاه فقلت اقضنى ثمن بكري قال\r\nلا أقضيك الا بختية فدعاني فأحسن قضائي ثم جاء أعرابي فقال اقضني بكري فقضاه\r\nبعيرا الحديث )\r\n","description":"","footnote":"","page_name":" 347 ","page_number":347},
  {"content":"\r\n\r\n","description":"","footnote":"","page_name":" 348 ","page_number":348},
  {"content":"\r\n\r\n","description":"","footnote":"","page_name":" 349 ","page_number":349},
  {"content":"\r\n\r\n","description":"","footnote":"","page_name":" 350 ","page_number":350},
  {"content":"\r\n\r\n","description":"","footnote":"","page_name":" 351 ","page_number":351},
  {"content":"\r\n\r\n","description":"","footnote":"","page_name":" 352 ","page_number":352},
  {"content":"\r\n\r\n","description":"","footnote":"","page_name":" 353 ","page_number":353},
  {"content":"\r\n\r\n","description":"","footnote":"","page_name":" 354 ","page_number":354},
  {"content":"\r\n\r\n","description":"","footnote":"","page_name":" 355 ","page_number":355},
  {"content":"\r\n\r\n","description":"","footnote":"","page_name":" 356 ","page_number":356},
  {"content":"\r\n\r\n","description":"","footnote":"","page_name":" 357 ","page_number":357},
  {"content":"\r\n\r\n","description":"","footnote":"","page_name":" 358 ","page_number":358},
  {"content":"\r\n\r\n","description":"","footnote":"","page_name":" 359 ","page_number":359},
  {"content":"\r\n\r\n","description":"","footnote":"","page_name":" 360 ","page_number":360},
  {"content":"\r\n\r\n","description":"","footnote":"","page_name":" 361 ","page_number":361},
  {"content":"\r\n\r\n","description":"","footnote":"","page_name":" 362 ","page_number":362},
  {"content":"\r\n\r\n","description":"","footnote":"","page_name":" 363 ","page_number":363},
  {"content":"\r\n\r\n","description":"","footnote":"","page_name":" 364 ","page_number":364},
  {"content":"\r\n\r\n","description":"","footnote":"","page_name":" 365 ","page_number":365},
  {"content":"\r\n\r\n","description":"","footnote":"","page_name":" 366 ","page_number":366},
  {"content":"\r\n\r\n","description":"","footnote":"","page_name":" 367 ","page_number":367},
  {"content":"\r\n\r\n","description":"","footnote":"","page_name":" 368 ","page_number":368},
  {"content":"\r\n\r\n","description":"","footnote":"","page_name":" 369 ","page_number":369},
  {"content":"\r\n\r\n","description":"","footnote":"","page_name":" 370 ","page_number":370},
  {"content":"\r\n\r\n","description":"","footnote":"","page_name":" 371 ","page_number":371},
  {"content":"\r\n\r\n","description":"","footnote":"","page_name":" 372 ","page_number":372},
  {"content":"\r\n( 1 ) ( حديث ) أن النبي صلى الله عليه وسلم نهى عن قرض جر منفعة وفى رواية كل قرض جر\r\nمنفعة فهو ربا قال عمر بن بدر في المغنى لم يصح فيه شئ وأما امام الحرمين فقال إنه صح وتبعه\r\nالغزالي وقد رواه الحرث بن أبي أسامة في مسنده من حديث على باللفظ الأول وفى اسناده\r\nسوار بن مصعب وهو متروك ورواه البيهقي في المعرفة عن فضالة بن عبيد موقوفا بلفظ كل\r\nقرض جر منفعة فهو وجه من وجوه الربا ورواه في السنن الكبرى عن ابن مسعود وأبي بن كعب\r\nوعبد الله بن سلام وابن عباس موقوفا عليهم *\r\n","description":"","footnote":"","page_name":" 373 ","page_number":373},
  {"content":"\r\n( 1 ) ( حديث ) عبد الله ابن عمرو أمرني النبي صلى الله عليه وسلم أن أجهز جيشا فنفذت الإبل\r\nفأمرني أن آخذ بعيرا ببعيرين إلى أجل تقدم في الربا *\r\n","description":"","footnote":"","page_name":" 374 ","page_number":374},
  {"content":"\r\n\r\n","description":"","footnote":"","page_name":" 375 ","page_number":375},
  {"content":"\r\n( 1 ) ( حديث ) خياركم أحسنكم قضاء . تقدم من حديث أبي هريرة قريبا *\r\n","description":"","footnote":"","page_name":" 376 ","page_number":376},
  {"content":"\r\n\r\n","description":"","footnote":"","page_name":" 377 ","page_number":377},
  {"content":"\r\n\r\n","description":"","footnote":"","page_name":" 378 ","page_number":378},
  {"content":"\r\n\r\n","description":"","footnote":"","page_name":" 379 ","page_number":379},
  {"content":"\r\n\r\n","description":"","footnote":"","page_name":" 380 ","page_number":380},
  {"content":"\r\n\r\n","description":"","footnote":"","page_name":" 381 ","page_number":381},
  {"content":"\r\n\r\n","description":"","footnote":"","page_name":" 382 ","page_number":382},
  {"content":"\r\n\r\n","description":"","footnote":"","page_name":" 383 ","page_number":383},
  {"content":"\r\n( 1 ) ( حديث ) أنه صلى الله عليه وسلم نهى عن سلف وبيع . البيهقي وغيره من حديث عمرو بن\r\nشعيب عن أبيه عن جده وقد تقدم *\r\n( قوله ) نهى السلف عن اقراض الولائد وكأنه تبع امام الحرمين فإنه كذا قال بل زاد\r\nأنه صح عنهم وأما الغزالي في الوسيط فعزاه إلى الصحابة وقد قال ابن حزم ما نعلم في هذا أصلا من\r\nكتاب ولا من رواية صحيحة ولا سقيمة ولا من قول صاحب ولا من اجماع ولا من قياس\r\n* * *\r\n\r\n","description":"","footnote":"","page_name":" 384 ","page_number":384}
  ]